<?xml version="1.0" encoding="utf-8"?>
<LanguageData id="한국어">
  <LanguageFile xml_path="KO/std_action_strings_xml_kor.xml" />
  <LanguageFile xml_path="KO/std_bandits_xml_kor.xml" />
  <LanguageFile xml_path="KO/std_caravans_xml_kor.xml" />
  <LanguageFile xml_path="KO/std_comment_on_action_strings_xml_kor.xml" />
  <LanguageFile xml_path="KO/std_comment_strings_xml_kor.xml" />
  <LanguageFile xml_path="KO/std_common_strings_xml_kor.xml" />
  <LanguageFile xml_path="KO/std_companion_strings_xml_kor.xml" />
  <LanguageFile xml_path="KO/std_concept_strings_xml_kor.xml" />
  <LanguageFile xml_path="KO/std_heroes_xml_kor.xml" />
  <LanguageFile xml_path="KO/std_location_complex_templates_xml_kor.xml" />
  <LanguageFile xml_path="KO/std_lords_xml_kor.xml" />
  <LanguageFile xml_path="KO/std_module_strings_xml_kor.xml" />
  <LanguageFile xml_path="KO/std_SandBox_GauntletUI_kor.xml" />
  <LanguageFile xml_path="KO/std_SandBox_ViewModelCollection_kor.xml" />
  <LanguageFile xml_path="KO/std_SandBox_View_kor.xml" />
  <LanguageFile xml_path="KO/std_SandBox_kor.xml" />
  <LanguageFile xml_path="KO/std_settlements_xml_kor.xml" />
  <LanguageFile xml_path="KO/std_spclans_xml_kor.xml" />
  <LanguageFile xml_path="KO/std_spkingdoms_xml_kor.xml" />
  <LanguageFile xml_path="KO/std_spprojects_xml_kor.xml" />
  <LanguageFile xml_path="KO/std_spspecialcharacters_xml_kor.xml" />
  <LanguageFile xml_path="KO/std_spworkshops_xml_kor.xml" />
  <LanguageFile xml_path="KO/std_TaleWorlds_CampaignSystem_kor.xml" />
  <LanguageFile xml_path="KO/std_TaleWorlds_CampaignSystem_ViewModelCollection_kor.xml" />
  <LanguageFile xml_path="KO/std_trait_strings_xml_kor.xml" />
  <LanguageFile xml_path="KO/std_voice_strings_xml_kor.xml" />
  <LanguageFile xml_path="KO/std_wanderer_strings_xml_kor.xml" />
  <LanguageFile xml_path="KO/std_world_lore_strings_xml_kor.xml" />
</LanguageData>