<?xml version="1.0" encoding="utf-8"?>
<base xmlns:xsi="http://www.w3.org/2001/XMLSchema-instance" xmlns:xsd="http://www.w3.org/2001/XMLSchema" type="string">
  <tags>
    <tag language="Português (BR)" />
  </tags>
  <strings>
    <string id="HB9emF7u" text="Falha ao iniciar sessão por expiração do tempo" />
    <string id="ph6rtI5J" text="Falha na inicialização da plataforma Xbox: {FAILREASON}" />
    <string id="Qb30URMY" text="Falha ao iniciar sessão do usuário: {FAILREASON}" />
    <string id="yWJcwCHf" text="Não foi possível obter a ID de Título do Xbox" />
  </strings>
</base>