<rhubarbResult>
  <metadata>
    <soundFile />
    <duration>2.66</duration>
  </metadata>
  <mouthCues>
    <mouthCue start="0.00" end="0.03">X</mouthCue>
    <mouthCue start="0.03" end="0.23">D</mouthCue>
    <mouthCue start="0.23" end="0.37">B</mouthCue>
    <mouthCue start="0.37" end="0.45">A</mouthCue>
    <mouthCue start="0.45" end="0.53">D</mouthCue>
    <mouthCue start="0.53" end="0.74">B</mouthCue>
    <mouthCue start="0.74" end="0.88">C</mouthCue>
    <mouthCue start="0.88" end="1.09">E</mouthCue>
    <mouthCue start="1.09" end="1.16">B</mouthCue>
    <mouthCue start="1.16" end="1.30">C</mouthCue>
    <mouthCue start="1.30" end="1.86">B</mouthCue>
    <mouthCue start="1.86" end="2.66">X</mouthCue>
  </mouthCues>
</rhubarbResult>