<rhubarbResult>
  <metadata>
    <soundFile />
    <duration>3.63</duration>
  </metadata>
  <mouthCues>
    <mouthCue start="0.00" end="0.08">X</mouthCue>
    <mouthCue start="0.08" end="0.19">B</mouthCue>
    <mouthCue start="0.19" end="0.44">D</mouthCue>
    <mouthCue start="0.44" end="0.51">C</mouthCue>
    <mouthCue start="0.51" end="0.88">B</mouthCue>
    <mouthCue start="0.88" end="1.16">E</mouthCue>
    <mouthCue start="1.16" end="1.65">F</mouthCue>
    <mouthCue start="1.65" end="1.73">A</mouthCue>
    <mouthCue start="1.73" end="1.80">C</mouthCue>
    <mouthCue start="1.80" end="2.00">F</mouthCue>
    <mouthCue start="2.00" end="2.08">A</mouthCue>
    <mouthCue start="2.08" end="2.39">B</mouthCue>
    <mouthCue start="2.39" end="2.74">C</mouthCue>
    <mouthCue start="2.74" end="3.63">X</mouthCue>
  </mouthCues>
</rhubarbResult>