<rhubarbResult>
  <metadata>
    <soundFile />
    <duration>2.27</duration>
  </metadata>
  <mouthCues>
    <mouthCue start="0.00" end="0.15">X</mouthCue>
    <mouthCue start="0.15" end="0.31">C</mouthCue>
    <mouthCue start="0.31" end="0.39">A</mouthCue>
    <mouthCue start="0.39" end="0.46">C</mouthCue>
    <mouthCue start="0.46" end="0.67">F</mouthCue>
    <mouthCue start="0.67" end="0.81">B</mouthCue>
    <mouthCue start="0.81" end="1.02">C</mouthCue>
    <mouthCue start="1.02" end="1.09">G</mouthCue>
    <mouthCue start="1.09" end="1.23">C</mouthCue>
    <mouthCue start="1.23" end="1.44">B</mouthCue>
    <mouthCue start="1.44" end="2.27">X</mouthCue>
  </mouthCues>
</rhubarbResult>