<rhubarbResult>
  <metadata>
    <soundFile />
    <duration>10.00</duration>
  </metadata>
  <mouthCues>
    <mouthCue start="0.00" end="0.23">X</mouthCue>
    <mouthCue start="0.23" end="0.29">F</mouthCue>
    <mouthCue start="0.29" end="0.42">C</mouthCue>
    <mouthCue start="0.42" end="0.56">H</mouthCue>
    <mouthCue start="0.56" end="0.63">C</mouthCue>
    <mouthCue start="0.63" end="1.40">B</mouthCue>
    <mouthCue start="1.40" end="1.61">F</mouthCue>
    <mouthCue start="1.61" end="1.75">B</mouthCue>
    <mouthCue start="1.75" end="1.82">D</mouthCue>
    <mouthCue start="1.82" end="2.17">B</mouthCue>
    <mouthCue start="2.17" end="2.45">X</mouthCue>
    <mouthCue start="2.45" end="2.93">B</mouthCue>
    <mouthCue start="2.93" end="3.00">G</mouthCue>
    <mouthCue start="3.00" end="3.08">A</mouthCue>
    <mouthCue start="3.08" end="3.14">B</mouthCue>
    <mouthCue start="3.14" end="3.20">C</mouthCue>
    <mouthCue start="3.20" end="3.76">B</mouthCue>
    <mouthCue start="3.76" end="3.90">G</mouthCue>
    <mouthCue start="3.90" end="4.11">F</mouthCue>
    <mouthCue start="4.11" end="4.18">C</mouthCue>
    <mouthCue start="4.18" end="4.32">E</mouthCue>
    <mouthCue start="4.32" end="4.39">B</mouthCue>
    <mouthCue start="4.39" end="4.53">G</mouthCue>
    <mouthCue start="4.53" end="4.60">C</mouthCue>
    <mouthCue start="4.60" end="4.67">B</mouthCue>
    <mouthCue start="4.67" end="4.81">G</mouthCue>
    <mouthCue start="4.81" end="4.95">E</mouthCue>
    <mouthCue start="4.95" end="5.30">F</mouthCue>
    <mouthCue start="5.30" end="5.44">B</mouthCue>
    <mouthCue start="5.44" end="5.65">E</mouthCue>
    <mouthCue start="5.65" end="6.07">B</mouthCue>
    <mouthCue start="6.07" end="6.42">C</mouthCue>
    <mouthCue start="6.42" end="6.49">B</mouthCue>
    <mouthCue start="6.49" end="6.70">F</mouthCue>
    <mouthCue start="6.70" end="6.77">B</mouthCue>
    <mouthCue start="6.77" end="6.84">C</mouthCue>
    <mouthCue start="6.84" end="6.98">B</mouthCue>
    <mouthCue start="6.98" end="7.05">C</mouthCue>
    <mouthCue start="7.05" end="7.12">B</mouthCue>
    <mouthCue start="7.12" end="7.20">A</mouthCue>
    <mouthCue start="7.20" end="7.33">G</mouthCue>
    <mouthCue start="7.33" end="7.75">F</mouthCue>
    <mouthCue start="7.75" end="8.15">X</mouthCue>
    <mouthCue start="8.15" end="8.43">F</mouthCue>
    <mouthCue start="8.43" end="8.48">E</mouthCue>
    <mouthCue start="8.48" end="8.66">C</mouthCue>
    <mouthCue start="8.66" end="8.73">G</mouthCue>
    <mouthCue start="8.73" end="8.80">C</mouthCue>
    <mouthCue start="8.80" end="9.01">B</mouthCue>
    <mouthCue start="9.01" end="9.22">F</mouthCue>
    <mouthCue start="9.22" end="9.36">B</mouthCue>
    <mouthCue start="9.36" end="9.57">C</mouthCue>
    <mouthCue start="9.57" end="9.71">B</mouthCue>
    <mouthCue start="9.71" end="10.00">X</mouthCue>
  </mouthCues>
</rhubarbResult>