<rhubarbResult>
  <metadata>
    <soundFile />
    <duration>4.66</duration>
  </metadata>
  <mouthCues>
    <mouthCue start="0.00" end="0.03">X</mouthCue>
    <mouthCue start="0.03" end="0.08">C</mouthCue>
    <mouthCue start="0.08" end="0.34">B</mouthCue>
    <mouthCue start="0.34" end="0.54">F</mouthCue>
    <mouthCue start="0.54" end="0.62">E</mouthCue>
    <mouthCue start="0.62" end="0.76">H</mouthCue>
    <mouthCue start="0.76" end="0.83">C</mouthCue>
    <mouthCue start="0.83" end="1.18">B</mouthCue>
    <mouthCue start="1.18" end="1.32">G</mouthCue>
    <mouthCue start="1.32" end="1.39">B</mouthCue>
    <mouthCue start="1.39" end="1.47">A</mouthCue>
    <mouthCue start="1.47" end="1.57">C</mouthCue>
    <mouthCue start="1.57" end="1.64">E</mouthCue>
    <mouthCue start="1.64" end="1.71">B</mouthCue>
    <mouthCue start="1.71" end="1.85">X</mouthCue>
    <mouthCue start="1.85" end="2.07">B</mouthCue>
    <mouthCue start="2.07" end="4.66">X</mouthCue>
  </mouthCues>
</rhubarbResult>