<rhubarbResult>
  <metadata>
    <soundFile />
    <duration>10.00</duration>
  </metadata>
  <mouthCues>
    <mouthCue start="0.00" end="0.03">X</mouthCue>
    <mouthCue start="0.03" end="0.13">F</mouthCue>
    <mouthCue start="0.13" end="0.41">C</mouthCue>
    <mouthCue start="0.41" end="1.20">X</mouthCue>
    <mouthCue start="1.20" end="1.32">G</mouthCue>
    <mouthCue start="1.32" end="1.60">B</mouthCue>
    <mouthCue start="1.60" end="1.67">G</mouthCue>
    <mouthCue start="1.67" end="1.76">A</mouthCue>
    <mouthCue start="1.76" end="2.08">B</mouthCue>
    <mouthCue start="2.08" end="2.15">G</mouthCue>
    <mouthCue start="2.15" end="2.43">C</mouthCue>
    <mouthCue start="2.43" end="2.57">B</mouthCue>
    <mouthCue start="2.57" end="2.64">F</mouthCue>
    <mouthCue start="2.64" end="2.71">B</mouthCue>
    <mouthCue start="2.71" end="2.99">F</mouthCue>
    <mouthCue start="2.99" end="3.17">X</mouthCue>
    <mouthCue start="3.17" end="4.21">B</mouthCue>
    <mouthCue start="4.21" end="4.28">E</mouthCue>
    <mouthCue start="4.28" end="4.35">F</mouthCue>
    <mouthCue start="4.35" end="4.42">B</mouthCue>
    <mouthCue start="4.42" end="4.49">G</mouthCue>
    <mouthCue start="4.49" end="4.56">B</mouthCue>
    <mouthCue start="4.56" end="4.70">C</mouthCue>
    <mouthCue start="4.70" end="4.91">B</mouthCue>
    <mouthCue start="4.91" end="5.46">X</mouthCue>
    <mouthCue start="5.46" end="5.59">G</mouthCue>
    <mouthCue start="5.59" end="5.73">C</mouthCue>
    <mouthCue start="5.73" end="5.92">B</mouthCue>
    <mouthCue start="5.92" end="6.10">C</mouthCue>
    <mouthCue start="6.10" end="6.73">B</mouthCue>
    <mouthCue start="6.73" end="6.82">A</mouthCue>
    <mouthCue start="6.82" end="10.00">X</mouthCue>
  </mouthCues>
</rhubarbResult>