<rhubarbResult>
  <metadata>
    <soundFile />
    <duration>12.72</duration>
  </metadata>
  <mouthCues>
    <mouthCue start="0.00" end="0.03">X</mouthCue>
    <mouthCue start="0.03" end="0.15">D</mouthCue>
    <mouthCue start="0.15" end="0.22">B</mouthCue>
    <mouthCue start="0.22" end="0.36">G</mouthCue>
    <mouthCue start="0.36" end="0.43">F</mouthCue>
    <mouthCue start="0.43" end="0.50">C</mouthCue>
    <mouthCue start="0.50" end="0.64">B</mouthCue>
    <mouthCue start="0.64" end="0.92">C</mouthCue>
    <mouthCue start="0.92" end="0.99">B</mouthCue>
    <mouthCue start="0.99" end="1.20">C</mouthCue>
    <mouthCue start="1.20" end="1.27">E</mouthCue>
    <mouthCue start="1.27" end="1.41">C</mouthCue>
    <mouthCue start="1.41" end="1.48">B</mouthCue>
    <mouthCue start="1.48" end="1.69">C</mouthCue>
    <mouthCue start="1.69" end="1.76">B</mouthCue>
    <mouthCue start="1.76" end="1.86">A</mouthCue>
    <mouthCue start="1.86" end="1.95">G</mouthCue>
    <mouthCue start="1.95" end="2.02">E</mouthCue>
    <mouthCue start="2.02" end="2.23">B</mouthCue>
    <mouthCue start="2.23" end="2.44">C</mouthCue>
    <mouthCue start="2.44" end="2.51">B</mouthCue>
    <mouthCue start="2.51" end="2.79">X</mouthCue>
    <mouthCue start="2.79" end="3.13">B</mouthCue>
    <mouthCue start="3.13" end="3.27">C</mouthCue>
    <mouthCue start="3.27" end="3.34">G</mouthCue>
    <mouthCue start="3.34" end="3.41">C</mouthCue>
    <mouthCue start="3.41" end="3.83">F</mouthCue>
    <mouthCue start="3.83" end="3.90">C</mouthCue>
    <mouthCue start="3.90" end="3.97">E</mouthCue>
    <mouthCue start="3.97" end="4.11">C</mouthCue>
    <mouthCue start="4.11" end="4.19">A</mouthCue>
    <mouthCue start="4.19" end="4.34">C</mouthCue>
    <mouthCue start="4.34" end="4.41">E</mouthCue>
    <mouthCue start="4.41" end="4.76">F</mouthCue>
    <mouthCue start="4.76" end="4.83">B</mouthCue>
    <mouthCue start="4.83" end="4.93">A</mouthCue>
    <mouthCue start="4.93" end="5.06">H</mouthCue>
    <mouthCue start="5.06" end="5.13">C</mouthCue>
    <mouthCue start="5.13" end="5.27">B</mouthCue>
    <mouthCue start="5.27" end="5.62">F</mouthCue>
    <mouthCue start="5.62" end="5.69">C</mouthCue>
    <mouthCue start="5.69" end="5.95">E</mouthCue>
    <mouthCue start="5.95" end="6.12">D</mouthCue>
    <mouthCue start="6.12" end="6.16">C</mouthCue>
    <mouthCue start="6.16" end="6.42">B</mouthCue>
    <mouthCue start="6.42" end="6.49">F</mouthCue>
    <mouthCue start="6.49" end="6.56">H</mouthCue>
    <mouthCue start="6.56" end="6.77">C</mouthCue>
    <mouthCue start="6.77" end="6.84">G</mouthCue>
    <mouthCue start="6.84" end="6.91">B</mouthCue>
    <mouthCue start="6.91" end="7.05">C</mouthCue>
    <mouthCue start="7.05" end="7.19">B</mouthCue>
    <mouthCue start="7.19" end="7.47">F</mouthCue>
    <mouthCue start="7.47" end="7.68">B</mouthCue>
    <mouthCue start="7.68" end="7.76">A</mouthCue>
    <mouthCue start="7.76" end="7.83">C</mouthCue>
    <mouthCue start="7.83" end="8.46">B</mouthCue>
    <mouthCue start="8.46" end="8.53">C</mouthCue>
    <mouthCue start="8.53" end="8.60">B</mouthCue>
    <mouthCue start="8.60" end="8.74">C</mouthCue>
    <mouthCue start="8.74" end="8.81">G</mouthCue>
    <mouthCue start="8.81" end="8.88">C</mouthCue>
    <mouthCue start="8.88" end="8.95">B</mouthCue>
    <mouthCue start="8.95" end="9.02">C</mouthCue>
    <mouthCue start="9.02" end="9.09">B</mouthCue>
    <mouthCue start="9.09" end="9.16">G</mouthCue>
    <mouthCue start="9.16" end="9.30">C</mouthCue>
    <mouthCue start="9.30" end="9.72">B</mouthCue>
    <mouthCue start="9.72" end="12.72">X</mouthCue>
  </mouthCues>
</rhubarbResult>