<?xml version="1.0" encoding="utf-8"?>
<base xmlns:xsi="http://www.w3.org/2001/XMLSchema-instance" xmlns:xsd="http://www.w3.org/2001/XMLSchema" type="string">
  <tags>
    <tag language="Polski" />
  </tags>
  <strings>
    <string id="024kHRwG" text="{.MP}Nomanides" />
    <string id="04dAbdjM" text="{.F}Nywia" />
    <string id="04zSjaRe" text="{.MP}Nartyros" />
    <string id="074bIPbm" text="{.MP}Llum" />
    <string id="0atYAnDF" text="{.MP}Tulul" />
    <string id="0DgWpr8b" text="{.MP}Dengul" />
    <string id="0dHy2430" text="{.F}Echalera" />
    <string id="0MJi7mre" text="{.F}Hiskazja" />
    <string id="0OFMT7AO" text="{.MP}Rotard" />
    <string id="0VZ5sROI" text="{.MP}Okhon" />
    <string id="0YAZ51bc" text="{.MP}Lorgand" />
    <string id="0znqTt5G" text="Banu Sarran" />
    <string id="0ZTMVxzw" text="{.MP}Lazif" />
    <string id="0ZXMKL4M" text="{.MP}Szawił" />
    <string id="17k0NVul" text="{.MP}Inrik" />
    <string id="1I3uRUGM" text="{.MP}Riman" />
    <string id="1JgWclmT" text="{.MP}Czorik" />
    <string id="1mhbWay3" text="{.F}Dinin" />
    <string id="1suLcaso" text="{.MP}Kunbert" />
    <string id="1Ww5lg6I" text="Pierwsi Wlandyjczycy przybyli zza morza jako mówiący językami wielu ludów najemnicy i awanturnicy. Za cesarski pieniądz strzegli granic przeciw nieposkromionym plemionom interioru. Nazwę wzięli od jednego ze swych pierwszych przywódców, Wilunda Śmiałego – po kalradyjsku Valandiona. Z czasem przekształciła się ona w słowo „Wlandyjczycy”. Ich niezrównana ciężka kawaleria miażdżyła cesarskich wrogów od pustkowi Aseraju po odległe stepy. Ubodzy w gotówkę urzędnicy wkrótce zaczęli jednak zamiast złota dawać im ziemię i tytuły, co chyba nie było szczególnie dalekowzroczną polityką. Wlandyjczycy osiedlili się, zaczęli zawierać małżeństwa i uprawiać rolę, a wkrótce przejęli dla siebie pobliskie cesarskie fortece. Są teraz niepodległym królestwem łączącym w swojej kulturze zarówno tradycje kalradyjskie, jak i te pochodzące z ich odległych ojczyzn." />
    <string id="25zTek7a" text="{.MP}Alachir" />
    <string id="26tqV3ak" text="{.F}Teuda" />
    <string id="26v27bu7" text="{.F}Aika" />
    <string id="29Ti1C0R" text="{.F}Selun" />
    <string id="2bNvfQny" text="fen Ruamor" />
    <string id="2mhCIkuB" text="{.MP}Dżaim" />
    <string id="2mWC6b8D" text="{.F}Sacha" />
    <string id="2s7Tb4NC" text="{.F}Fionara" />
    <string id="2Sn4uK35" text="{.F}Orgunda" />
    <string id="2uKoNaSG" text="{.MP}Denos" />
    <string id="2YbgWjTK" text="{.F}Emina" />
    <string id="38o99yqa" text="{.MP}Borcza" />
    <string id="3apHdqU7" text="{.MP}Ingczit{.nnp}" />
    <string id="3bIc2X2l" text="{.F}Waminesa" />
    <string id="3EZMoUlp" text="{.MP}Narmys" />
    <string id="3ipKaDWU" text="{.MP}Natti" />
    <string id="3jXYDAIo" text="fen Cearthad" />
    <string id="3LHG5Efi" text="{.F}Ajasa" />
    <string id="3LMFx9dL" text="{.F}Friduna" />
    <string id="3mdyg3nF" text="{.MP}Dawobard" />
    <string id="3NRUkzaV" text="{.F}Dżasugan" />
    <string id="3oeb8Bav" text="{.MP}Dżasyd" />
    <string id="3pgwKPsf" text="{.MP}Karais" />
    <string id="3RbayfTG" text="{.F}Ascytala" />
    <string id="3rXHA6fI" text="{.MP}Samar" />
    <string id="4833ZS9c" text="{.MP}Aldusunit{.nnp}" />
    <string id="4ABVdxKn" text="{.MP}Tyl" />
    <string id="4bQbv3oN" text="{.F}Arga" />
    <string id="4BXAmC6W" text="fen Beannis" />
    <string id="4dJ3pLxu" text="{.MP}Hemel" />
    <string id="4JfwP1T6" text="{.MP}Badur" />
    <string id="4kvs02aU" text="{.MP}Robrik" />
    <string id="4KZXSIjc" text="{.MP}Porew" />
    <string id="4mUKn5Hg" text="{.MP}Szerald" />
    <string id="4Su3mMpd" text="{.F}Iwaren" />
    <string id="4Vd1TXpN" text="{.F}Anwyn" />
    <string id="4xnag9e8" text="{.MP}Itsul" />
    <string id="4ZhqF8EB" text="{.MP}Arszul" />
    <string id="4zoraJq7" text="{.MP}Janagur" />
    <string id="528J5D3b" text="{.F}Jasmila" />
    <string id="5LY1iQWh" text="{.MP}Jakus" />
    <string id="5ntTjanU" text="{.MP}Dżundżad" />
    <string id="5o1bM9G0" text="{.F}Wasinia" />
    <string id="5O81vNIS" text="{.MP}Taja" />
    <string id="5oRDaemv" text="{.MP}Aerik" />
    <string id="5QHosdnk" text="{.MP}Sudais" />
    <string id="5QLjWfGN" text="{.MP}Sikard" />
    <string id="5vo7WX5W" text="{.F}Amul" />
    <string id="5VZ0GF6Y" text="{.F}Zalisa" />
    <string id="5YsDdW9s" text="{.MP}Sorgard" />
    <string id="5zxaCgd6" text="{.MP}Marandżit{.nnp}" />
    <string id="63ZZltcm" text="{.MP}Zalastros{.nnp}" />
    <string id="68JEMvYl" text="{.MP}Griff" />
    <string id="6AwXDgIK" text="{.MP}Mych" />
    <string id="6bBj5HgU" text="{.MP}Garain" />
    <string id="6d09RcZT" text="{.F}Sulata" />
    <string id="6fbD85kZ" text="{.F}Kara" />
    <string id="6FebKbCp" text="{.MP}Szel" />
    <string id="6fENuhfZ" text="{.F}Sybuga" />
    <string id="6hCz0ZFN" text="{.MP}Byram" />
    <string id="6I6GVFpq" text="{.F}Karmenet" />
    <string id="6IDmRZ5k" text="{.MP}Festos" />
    <string id="6LRFHHqT" text="{.F}Imulir" />
    <string id="6p3qkhil" text="{.MP}Bilija" />
    <string id="6pAsFGvw" text="{.F}Abeil" />
    <string id="75Wlqr3W" text="{.MP}Alpan" />
    <string id="7Gt27Agy" text="{.MP}Malub" />
    <string id="7hYr7jQ7" text="{.MP}Leutros" />
    <string id="7Jd3g0XP" text="{.F}Isilflaed" />
    <string id="7lixVdYb" text="{.MP}Erchisasos{.nnp}" />
    <string id="7Lkbtnet" text="{.F}Luwina" />
    <string id="7MpWM3y3" text="{.MP}Himil" />
    <string id="7n7V9Va5" text="{.F}Iria" />
    <string id="7No7syyO" text="{.F}Penek" />
    <string id="7oBUn2V1" text="Banu Rawi" />
    <string id="7T5z6N7e" text="{.MP}Ulasław" />
    <string id="7uBgKkLK" text="{.F}Andżykin" />
    <string id="7uj8QoPA" text="{.F}Feteir" />
    <string id="7UU9TwUC" text="{.F}Dalaj" />
    <string id="83e9F9bC" text="{.MP}Brungalter" />
    <string id="86iEfIma" text="{.MP}Funder" />
    <string id="86L9ayRV" text="{.F}Athlian" />
    <string id="86LT9H6v" text="Banu Fasus" />
    <string id="8bWBc3sK" text="{.MP}Alajen" />
    <string id="8C19nvLL" text="{.MP}Altegar" />
    <string id="8CQuY3RO" text="{.MP}Munitydes{.nnp}" />
    <string id="8CZvFqH7" text="{.MP}Toczi" />
    <string id="8IcnIQdq" text="{.MP}Gusur" />
    <string id="8jwqNls9" text="{.MP}Khomar" />
    <string id="8kajrmx4" text="{.MP}Galrik" />
    <string id="8KoaUqQz" text="{.MP}Helmold" />
    <string id="8Rirvd8I" text="{.F}Larka" />
    <string id="8RolYmff" text="{.F}Zuwaira" />
    <string id="8SBw5PzN" text="{.MP}Armund" />
    <string id="8UGqSVH5" text="{.MP}Natun" />
    <string id="8YhNZHtC" text="{.MP}Fenton" />
    <string id="93hivVp6" text="{.F}Donysa" />
    <string id="9AOFkQBo" text="{.F}Elta" />
    <string id="9aPxu1EB" text="{.F}Tinab" />
    <string id="9HcXWNoh" text="{.MP}Folk" />
    <string id="9I9ziX31" text="{.F}Wilatruda" />
    <string id="9l3RSCJp" text="{.MP}Kolsund" />
    <string id="9mQuSI3c" text="{.MP}Tukazys" />
    <string id="9pnUaj0g" text="{.F}Eliaksza" />
    <string id="9SJa91sZ" text="{.F}Marena" />
    <string id="9vBp5E0Q" text="{.MP}Derngil" />
    <string id="9WMeUGTy" text="{.F}Caelis" />
    <string id="A0Qwy1ag" text="{.MP}Khakhun" />
    <string id="a2AjI8nc" text="Aserajczycy to władcy Nahasy, Brązowej Pustyni, która leży w południowej części Kalradii. Dla przybysza z zewnątrz wygląda zapewne na pustkowie – morze wydm poprzecinane żwirowiskami i skałami wulkanicznymi. Pod ziemią jednak można znaleźć wodę; zbiera się ona w depresjach lub pod wadi, które bywają wręcz czasem znienacka zalewane. Dużo jest jej też w oazach, w których osiedlają się ludzie. Lud ten dzieli się na dziesiątki klanów i podklanów, z których każdy prowadzi pieczołowitą genealogię. Wszystkie te rody razem znane są jako Banu Asera, synowie Asery. Ich specyficzne poczucie więzi etnicznej wynika ze wspólnego pochodzenia, które wiążą z tym właśnie legendarnym patriarchą. Swoje znaczne bogactwo i władzę zawdzięczają kontroli nad nielicznymi źródłami wody, pozwalającymi karawanom z odległych krain przekroczyć pustynię." />
    <string id="A2AYaNWM" text="{.MP}Orig" />
    <string id="a4hrvaEQ" text="{.MP}Daliger" />
    <string id="A8E9c4RM" text="{.MP}Emenkard" />
    <string id="aaOSBHrI" text="{.MP}Dynamontes{.nnp}" />
    <string id="AaoxZ4pn" text="fen Diall" />
    <string id="aaXaxmii" text="{.MP}Sadżjut{.nnp}" />
    <string id="Abzr6Dbv" text="{.MP}Darbard" />
    <string id="aCFsI8g6" text="fen Galonin" />
    <string id="aCTplh2G" text="{.MP}Wortert" />
    <string id="AcUEb8zX" text="{.MP}Korot" />
    <string id="aDAJGO4y" text="{.MP}Galtar" />
    <string id="AEaRpupL" text="{.MP}Ocheros" />
    <string id="AeNqteUX" text="{.MP}Zebales{.nnp}" />
    <string id="aH2ncPbK" text="{.MP}Zalasos" />
    <string id="AKhO9Y9c" text="{.MP}Jolugu" />
    <string id="am2UnbAK" text="{.MP}Menor" />
    <string id="AMbdha2J" text="{.MP}Chemnir" />
    <string id="amlzciqP" text="{.MP}Ukazjos" />
    <string id="AMmJVlrt" text="{.F}Kirasława" />
    <string id="Ao69q2aY" text="{.F}Pera" />
    <string id="aqd6QHES" text="{.F}Janab" />
    <string id="aqx7Txyy" text="{.MP}Tuwul" />
    <string id="aRiVb65B" text="{.MP}Dadżu" />
    <string id="aTcSQ7MY" text="{.MP}Oto" />
    <string id="au6vdzxN" text="{.MP}Gan" />
    <string id="aU9Cbb7j" text="{.MP}Atrar" />
    <string id="Av5aCluG" text="{.MP}Swato" />
    <string id="AWM3jbaZ" text="{.MP}Adżin" />
    <string id="Ax9OkgL5" text="Mgliste wzgórza północno-zachodniej Kalradii zamieszkane są przez batańskie klany, które dawniej zamieszkiwały większość kontynentu. Ich fortece na wzgórzach były świadkami niezliczonych wojen toczonych z najeźdźcami z dalekich krajów. Najpierw były to cesarskie legiony, w ostatnich czasach zaś rosnące w siłę królestwa Sturgii i Wlandii. Batowie są mistrzami długiego łuku, nocnych napaści, nagłych i niespodziewanych szarż z linii lasu. Wielbią odwagę, ale szczególnie cenią taką, w której drzemie też nuta złośliwości – spryt złodzieja bydła umiejącego zniknąć we mgle z całym stadem czy śmiałość czempiona, który przyjeżdża na ucztę rodu rywala i zabawiając gospodarzy anegdotką z bitwy, wyciąga dla ilustracji pamiątkę: czaszkę ich krewniaka." />
    <string id="aXwDg9VT" text="{.MP}Olokchaj{.nnp}" />
    <string id="Ayb3bCJn" text="{.MP}Artobald" />
    <string id="AYdwWae6" text="{.F}Ceatra" />
    <string id="aYiL7eDM" text="{.MP}Ilmir" />
    <string id="aYr6ovxb" text="{.F}Ragin" />
    <string id="b0rI89ob" text="{.F}Hara" />
    <string id="B15WfmQT" text="{.F}Gisilchild" />
    <string id="b6Ml7BkH" text="{.F}Weronet" />
    <string id="b7PVGEFM" text="{.MP}Lat" />
    <string id="B7zKKiYQ" text="{.MP}Tatik" />
    <string id="b8pMwtQu" text="{.MP}Terard" />
    <string id="Ba8jWKUq" text="{.F}Manachilda" />
    <string id="bBD4tF2y" text="{.MP}Moroczowing{.nnp}" />
    <string id="bbJLOMhl" text="{.MP}Pelisor" />
    <string id="BD4XeP07" text="{.MP}Mikri" />
    <string id="bdH1JEma" text="{.F}Jachim" />
    <string id="bdhXiiWK" text="{.F}Rajma" />
    <string id="begCei6W" text="fen Domus" />
    <string id="BfbZAB2K" text="{.F}Kanizat" />
    <string id="bFCk1Jrn" text="{.MP}Anhalm" />
    <string id="BGHBvAK1" text="{.MP}Kuliat" />
    <string id="bgNQtbS7" text="Banu Nir" />
    <string id="bHh03ob0" text="{.N}Wakken" />
    <string id="BIAEZaVx" text="{.F}Randana" />
    <string id="bLY1zbNI" text="{.MP}Zwatim" />
    <string id="bm9surN9" text="{.MP}Ubold" />
    <string id="bNj9gI2y" text="{.MP}Astin" />
    <string id="Bo5Xkd3e" text="{.MP}Erban" />
    <string id="bopqRUEQ" text="{.MP}Papenbard" />
    <string id="boUKXQz0" text="{.F}Margund" />
    <string id="BrI1aJdo" text="{.MP}Rukanowing{.nnp}" />
    <string id="Bt4MdhYE" text="{.F}Olguna" />
    <string id="Btb7NzFM" text="{.F}Szima" />
    <string id="bU46gvya" text="{.MP}Wulfyr" />
    <string id="BUbf73N2" text="{.MP}Gongke" />
    <string id="bVtVsEUr" text="{.MP}Gulassen" />
    <string id="bwabyQPy" text="{.F}Ikren" />
    <string id="BWEmxWv0" text="{.F}Igunta" />
    <string id="BxdYS56H" text="{.MP}Urentur" />
    <string id="By82n3gR" text="Banu Aska" />
    <string id="bzaLf3EU" text="{.MP}Magan" />
    <string id="bzXmtoC6" text="{.MP}Koleg" />
    <string id="C2yNuOKd" text="{.F}Beswinda" />
    <string id="c39lybQJ" text="Banu Dżulul" />
    <string id="C4akgRTN" text="{.F}Milisa" />
    <string id="C7aaPCCs" text="{.F}Wanalind" />
    <string id="cdQO1eLv" text="{.MP}Hasseid" />
    <string id="cEV3G3k8" text="{.MP}Stenalf" />
    <string id="CgwHKuzD" text="{.F}Beltruda" />
    <string id="CiJB8ISH" text="{.MP}Olorun" />
    <string id="Cj8vDOqR" text="{.F}Rahan" />
    <string id="cjYLX7sZ" text="{.MP}Weliszyn" />
    <string id="CoYOwpLP" text="{.MP}Dawan" />
    <string id="cpkNaEmz" text="{.MP}Waton" />
    <string id="cqSaKXzl" text="{.F}Mata" />
    <string id="CSDne5ja" text="{.MP}Kurdiut{.nnp}" />
    <string id="CSizDomP" text="{.MP}Ospak" />
    <string id="ctJub9Ah" text="{.MP}Kirinowing{.nnp}" />
    <string id="CuocGtTq" text="{.MP}Lestaros{.nnp}" />
    <string id="cv1QgU1H" text="{.MP}Pazel" />
    <string id="Cxazvjr3" text="{.F}Tamarea" />
    <string id="cxNCgqkI" text="{.F}Litka" />
    <string id="CXpnTfdk" text="{.MP}Guldrimand" />
    <string id="Cy8doiyv" text="{.MP}Lamark" />
    <string id="CYxjotI2" text="fen Krusak" />
    <string id="CYXRzc1D" text="{.F}Wisan" />
    <string id="D2r7VbZ8" text="{.MP}Talimund" />
    <string id="D4Ea4QaV" text="{.MP}Szulun" />
    <string id="DaCppjI9" text="{.MP}Ulpo" />
    <string id="DakafAXa" text="{.MP}Zamantowing{.nnp}" />
    <string id="daulkQvv" text="{.F}Brinia" />
    <string id="DBHAFW5k" text="{.MP}Osrik" />
    <string id="dey9d9DX" text="{.MP}Kasjowing{.nnp}" />
    <string id="dFHXmyaj" text="{.MP}Tandred" />
    <string id="DfZ5oi0O" text="{.F}Ragna" />
    <string id="DiB4ukeK" text="{.MP}Elisos{.nnp}" />
    <string id="DiGVNCZ1" text="{.MP}Torgud" />
    <string id="DkXPe3A3" text="{.MP}Newig" />
    <string id="dLOlnl8m" text="{.F}Palizyra" />
    <string id="DO1lhJIo" text="{.F}Tala" />
    <string id="dP5A3wwT" text="{.MP}Boskorik" />
    <string id="dPeYqphG" text="{.MP}Tunryk" />
    <string id="Du2Xg6rp" text="{.F}Gertlind" />
    <string id="DxU5mVDg" text="{.MP}Piasowing{.nnp}" />
    <string id="DYdI0faN" text="{.MP}Strakanastes{.nnp}" />
    <string id="DygS1Bef" text="Banu Muszala" />
    <string id="E1NB09bP" text="{.MP}Otsamides" />
    <string id="E1NWbOR8" text="{.MP}Buszul" />
    <string id="e4jAHUX0" text="{.F}Tymata" />
    <string id="e52LPp57" text="{.MP}Udris" />
    <string id="e6goEM5b" text="{.MP}Waldym" />
    <string id="e7dayl1i" text="{.MP}Mawinon" />
    <string id="eAro6IVf" text="{.MP}Szalar" />
    <string id="EbkJbzwO" text="Banu Unut" />
    <string id="eCCuztOS" text="{.F}Moera" />
    <string id="ecJRFHyY" text="{.F}Gizeta" />
    <string id="ed3sErKY" text="{.MP}Ilgaj" />
    <string id="egOzKsKS" text="{.MP}Kannar" />
    <string id="eJh7b90l" text="{.MP}Forenkard" />
    <string id="ek1Q2TJz" text="{.MP}Polon" />
    <string id="EKUSZBBj" text="{.MP}Wusur" />
    <string id="ELpRLYQt" text="{.F}Dżalin" />
    <string id="eMcQ35QA" text="{.MP}Radul" />
    <string id="Emsd1xmS" text="{.MP}Daszwal" />
    <string id="eNSZGTbN" text="{.MP}Doronowing{.nnp}" />
    <string id="eoF4TEr2" text="{.F}Daliset" />
    <string id="eOHeCKxn" text="{.F}Dżespara" />
    <string id="epxmhQav" text="{.F}Darinia" />
    <string id="eRg4Ngl1" text="{.MP}Farchasys{.nnp}" />
    <string id="eRh71UOr" text="{.MP}Ulgaryk" />
    <string id="ESKeInbq" text="{.MP}Aran" />
    <string id="EUQTT8so" text="{.MP}Oszir" />
    <string id="euyyBbjq" text="{.MP}Foliorowing{.nnp}" />
    <string id="evXLa2XX" text="{.MP}Farim" />
    <string id="EY0CcPfr" text="{.MP}Dinorik" />
    <string id="eYY8319F" text="{.MP}Dalibol" />
    <string id="f0NUMdNu" text="{.MP}Demerken{.nnp}" />
    <string id="f7u2p3x3" text="{.MP}Rutwar" />
    <string id="fAKa9JfU" text="{.MP}Natanys{.nnp}" />
    <string id="FakFqJf1" text="{.MP}Eurtymides{.nnp}" />
    <string id="fDbOCRMM" text="Banu Szum" />
    <string id="Fe90zVYF" text="{.F}Soeras" />
    <string id="fG19XSVm" text="{.MP}Rugan" />
    <string id="FIIZNV4F" text="{.MP}Acoryk" />
    <string id="FkbO2Abd" text="{.MP}Kras" />
    <string id="fkP7RRFe" text="{.F}Gerta" />
    <string id="FlexUfSP" text="{.F}Aliwar" />
    <string id="Fn064VUZ" text="{.MP}Zutyr" />
    <string id="FNHFzVCU" text="{.MP}Edwain" />
    <string id="fsOUhzLv" text="{.MP}Dżalos{.nnp}" />
    <string id="fUQlCkCQ" text="{.MP}Anbard" />
    <string id="FVDbGQXF" text="{.MP}Hamindar" />
    <string id="FVl3D2qT" text="{.MP}Meones{.nnp}" />
    <string id="FwcFIHfl" text="{.MP}Sewelar" />
    <string id="fWKnmnXb" text="{.MP}Taq" />
    <string id="fXgftgNv" text="{.MP}Afanys" />
    <string id="fydMDGtL" text="{.MP}Ferkread" />
    <string id="fYN6Aawl" text="{.MP}Kirasław" />
    <string id="FyVS24JZ" text="{.MP}Chundal" />
    <string id="g7etVhSO" text="{.MP}Sumessos{.nnp}" />
    <string id="G92bovut" text="{.MP}Mornid" />
    <string id="Ga3uaJY1" text="{.F}Teraflaed" />
    <string id="GaMUU2Pf" text="{.MP}Kaupi" />
    <string id="GBfFp7bW" text="fen Loen" />
    <string id="gC1paDtD" text="{.MP}Jerczowing{.nnp}" />
    <string id="GcgpbmWB" text="{.MP}Dżintasos{.nnp}" />
    <string id="gDMdWisO" text="{.MP}Hakr" />
    <string id="gG1O5V1n" text="{.F}Olianar" />
    <string id="GK18UxoX" text="{.MP}Hur" />
    <string id="gmD9mgR1" text="{.F}Synira" />
    <string id="GqEEIYay" text="{.F}Tilzad" />
    <string id="gqJUdECJ" text="{.F}Daellian" />
    <string id="gSHrv734" text="{.MP}Sorgar" />
    <string id="gsY9oKND" text="{.MP}Czusuntaj" />
    <string id="gU5cMdTT" text="{.F}Norena" />
    <string id="Gv5vdqxI" text="{.MP}Borwald" />
    <string id="Gwfb6O5O" text="{.F}Eira" />
    <string id="gxHrt6bC" text="{.MP}Faminor" />
    <string id="gzej3EbY" text="{.MP}Tulwo" />
    <string id="GZXVCS5B" text="{.F}Melind" />
    <string id="H1OFdfEe" text="{.F}Isna" />
    <string id="h6dabKXz" text="{.F}Reissen" />
    <string id="H7oJaxqM" text="{.F}Relasa" />
    <string id="h8DsXm7X" text="{.F}Achena" />
    <string id="hBuBpxjb" text="{.F}Kaidi" />
    <string id="HcmkBkYp" text="{.MP}Wigoter" />
    <string id="hdwBL8kp" text="{.F}Soregun" />
    <string id="HEGo3ArK" text="{.MP}Atis" />
    <string id="hF3F3u8u" text="{.MP}Duwain" />
    <string id="HMCZ2w9t" text="{.F}Anaheid" />
    <string id="Ho6zsGTI" text="{.MP}Sachanion" />
    <string id="HPrHkie6" text="{.MP}Fenigos{.nnp}" />
    <string id="hreO0wwb" text="{.F}Nerea" />
    <string id="HSpdZCr5" text="{.MP}Nebranos{.nnp}" />
    <string id="hsqDfT2j" text="{.MP}Jatan" />
    <string id="htJuLron" text="{.MP}Warag" />
    <string id="hTw3MjbR" text="{.MP}Ekard" />
    <string id="HwCJfTC2" text="{.F}Deni" />
    <string id="hWKKCdeX" text="{.MP}Mulum" />
    <string id="HXEoaiFU" text="{.MP}Sordżi" />
    <string id="HxKE18yl" text="{.MP}Laswak" />
    <string id="hyOgAehG" text="{.MP}Emarys" />
    <string id="I0ZfrCml" text="{.MP}Huskur" />
    <string id="i9bQ8UoK" text="{.MP}Żelik" />
    <string id="i9ZDrsi1" text="{.MP}Rafard" />
    <string id="IaBXamj4" text="{.MP}Daniwan" />
    <string id="IcB0xdbd" text="Banu Damin" />
    <string id="IDeemU90" text="{.F}Roslind" />
    <string id="ieube15m" text="{.F}Zahara" />
    <string id="iFJbnbCQ" text="{.MP}Agdil" />
    <string id="ig8zAo8f" text="{.MP}Ori" />
    <string id="IHhWB1aa" text="Darszi" />
    <string id="iiGXfCWd" text="{.F}Menar" />
    <string id="IJlw8V5D" text="{.F}Mistesa" />
    <string id="iJvIH6NP" text="{.MP}Dżuteros" />
    <string id="IK7uQU2p" text="{.MP}Lasyrys{.nnp}" />
    <string id="IkTCwsB8" text="{.MP}Kol" />
    <string id="ild3wLKb" text="{.MP}Pylitaks{.nnp}" />
    <string id="iltXQqgS" text="{.MP}Turwald" />
    <string id="IlwK5VaT" text="fen Parrac" />
    <string id="imBaF78b" text="{.F}Tuneika" />
    <string id="iNFahwv3" text="{.F}Nia" />
    <string id="IpC3oUbT" text="{.MP}Amaldulf" />
    <string id="iQbFDpKT" text="fen Earach" />
    <string id="irccq0qs" text="Banu Laik" />
    <string id="iTRV8m4Y" text="{.MP}Rylan" />
    <string id="IVHobRWE" text="{.MP}Uszarowing{.nnp}" />
    <string id="Iwe7Xpke" text="Banu Kinian" />
    <string id="J1s05Ovk" text="{.MP}Czarait{.nnp}" />
    <string id="j5HUaQ1a" text="{.MP}Azir" />
    <string id="J5i4h7JC" text="{.F}Kela" />
    <string id="J5kC0K3W" text="{.MP}Gutrag" />
    <string id="j6K4Z1L6" text="{.MP}Jalyr" />
    <string id="j8IOY5Cy" text="{.F}Luona" />
    <string id="jACaGLM5" text="{.MP}Salulk" />
    <string id="jCrbe08Y" text="{.F}Olawyn" />
    <string id="jcUgdBEo" text="{.MP}Unggun{.nnp}" />
    <string id="jeYqsu2T" text="{.MP}Normund" />
    <string id="jFdZ7mlB" text="{.F}Ilikki" />
    <string id="jFRrRgJx" text="{.MP}Gilward" />
    <string id="jgr2xo9r" text="{.MP}Darim" />
    <string id="jhlwsyqq" text="{.MP}Chromasos{.nnp}" />
    <string id="jhQkgQci" text="{.MP}Bajczar" />
    <string id="jhT7CfhM" text="{.MP}Aiwar" />
    <string id="JJtww9pt" text="{.MP}Ariusz" />
    <string id="jJV5Tn09" text="{.F}Tetyklesa" />
    <string id="jKviMpbP" text="{.MP}Kalradyjczyk" />
    <string id="JMiahwuO" text="fen Niabar" />
    <string id="jMPWSzAi" text="{.F}Loen" />
    <string id="jqaH0a35" text="{.MP}Tymanowing{.nnp}" />
    <string id="jqaPJbpP" text="{.MP}Urgil" />
    <string id="JQdqGaaB" text="{.F}Izybala" />
    <string id="JR1LKjIc" text="{.F}Kalisa" />
    <string id="Jr84qoAW" text="{.MP}Etenbold" />
    <string id="JUPUxuoe" text="{.MP}Kanbadar" />
    <string id="jVPr0ZzB" text="{.MP}Achyr" />
    <string id="jwcpnm8K" text="{.F}Eidenor" />
    <string id="K2UdjFvi" text="{.MP}Orunhard" />
    <string id="k37KKJkw" text="{.F}Kun" />
    <string id="K3fAPP5V" text="fen Ramennon" />
    <string id="K4UdL65N" text="{.MP}Lyd" />
    <string id="KbIHavJj" text="{.MP}Borabos" />
    <string id="kErcuRlk" text="{.MP}Ajjam" />
    <string id="kEw7yody" text="{.MP}Wolg" />
    <string id="kFYtFka8" text="{.F}Echa" />
    <string id="kIrWyLut" text="{.MP}Undgar" />
    <string id="kL0ldFLG" text="{.MP}Pekko" />
    <string id="KmAOMxqy" text="{.MP}Dawalan" />
    <string id="KmzQabkH" text="{.MP}Hiwan" />
    <string id="KPQqENbd" text="{.F}Karynila" />
    <string id="krMVSoId" text="{.F}Bautan" />
    <string id="KSsRA8xm" text="{.MP}Munim" />
    <string id="kUnGuyKG" text="{.MP}Garwi" />
    <string id="kWEta4kl" text="{.MP}Lamkard" />
    <string id="kWiQaFLM" text="{.MP}Delikos{.nnp}" />
    <string id="L0fuYckc" text="{.F}Friga" />
    <string id="L4XUK5n4" text="Banu Jatasz" />
    <string id="l95tJ2ly" text="{.MP}Nerrik" />
    <string id="la6HgVXN" text="{.MP}Mitunis" />
    <string id="lac74G8a" text="{.F}Agateuda" />
    <string id="lB7b7N1b" text="{.F}Dewen" />
    <string id="LbCcOORX" text="{.MP}Ongker" />
    <string id="lbNiWBRN" text="{.MP}Talryk" />
    <string id="lbTMVAcI" text="{.MP}Lerozjon" />
    <string id="Lcbrsqw8" text="{.MP}Sjawerowing{.nnp}" />
    <string id="LfP4vsfD" text="{.F}Sur" />
    <string id="lGRde77R" text="{.F}Anahita" />
    <string id="lhiAWoFw" text="{.MP}Sunit{.nnp}" />
    <string id="LipFTLvz" text="{.MP}Ubczit{.nnp}" />
    <string id="ljYVVV1s" text="{.F}Luka" />
    <string id="lMMbmuwp" text="{.F}Izygunda" />
    <string id="lMrP68Ba" text="{.MP}Grynad" />
    <string id="lMxYCQYF" text="{.MP}Teminides{.nnp}" />
    <string id="lpbIXNdK" text="{.MP}Suratowing{.nnp}" />
    <string id="LpLL0m3O" text="{.MP}Arlech" />
    <string id="lsOtNjxl" text="{.MP}Manitesos{.nnp}" />
    <string id="Lv753Nnn" text="{.F}Zylata" />
    <string id="LX1YS9DW" text="{.F}Lazylea" />
    <string id="LZ2nBcdv" text="{.F}Lis" />
    <string id="M1ORaYny" text="{.MP}Pol" />
    <string id="M2CFIsZU" text="fen Lanor" />
    <string id="m8dVlsEy" text="{.MP}Chym" />
    <string id="M9CWBbMe" text="{.MP}Ranos" />
    <string id="M9gqEb6D" text="{.MP}Radan" />
    <string id="Ma855h44" text="{.F}Iona" />
    <string id="Mc58AHLa" text="{.MP}Norbrand" />
    <string id="mDZqpa9Z" text="{.MP}Sandżar" />
    <string id="meNjBd0K" text="{.F}Zania" />
    <string id="MEtblzaV" text="{.F}Gunefer" />
    <string id="mfu9UqLL" text="{.MP}Szemyr" />
    <string id="MgDUudOx" text="{.MP}Balastisos{.nnp}" />
    <string id="MHT9jCqB" text="fen Tuil" />
    <string id="MjZumz0j" text="{.MP}Tokit{.nnp}" />
    <string id="Ml5KBonI" text="{.F}Tosui" />
    <string id="MN8aE2yP" text="{.MP}Karoger" />
    <string id="MNFMqV3n" text="{.MP}Lyfris" />
    <string id="MpZCQ0z1" text="{.MP}Breadan" />
    <string id="mqkSkCBX" text="{.MP}Uluwi" />
    <string id="mQStUNPe" text="{.MP}Kazam" />
    <string id="MRTWZuF4" text="{.MP}Kilam" />
    <string id="muB0Y0iv" text="{.MP}Botero" />
    <string id="mWCY0aSL" text="{.F}Wara" />
    <string id="MwPMFIz0" text="{.MP}Bagbajar" />
    <string id="N0cNsII3" text="{.F}Safija" />
    <string id="N4y8hPX9" text="{.F}Asgerta" />
    <string id="N7CGgRs5" text="{.MP}Cuban" />
    <string id="NAVXhanI" text="{.MP}Jarli" />
    <string id="NbprLzeU" text="{.MP}Dadzerowing{.nnp}" />
    <string id="ncEWiljT" text="{.F}Ria" />
    <string id="NeFDHnOS" text="{.F}Mirim" />
    <string id="NFIQZOPQ" text="{.MP}Leozjos" />
    <string id="NH6avjbc" text="{.MP}Falsewor" />
    <string id="nhwnbFJ0" text="{.F}Galaza" />
    <string id="NIcee06W" text="{.MP}Wangwajag" />
    <string id="nisA6W98" text="{.MP}Bahesztur" />
    <string id="NJvui1La" text="{.MP}Iskar" />
    <string id="NLXHafGS" text="{.MP}Gissinowing{.nnp}" />
    <string id="nOJ9W5FE" text="{.F}Brunda" />
    <string id="NqhPOiMQ" text="{.MP}Ulusumaj" />
    <string id="nqxxr9We" text="{.MP}Gawalon" />
    <string id="NTRPMben" text="{.MP}Atragorys{.nnp}" />
    <string id="nTYJWGAa" text="{.F}Szata" />
    <string id="NxDJcR2c" text="{.MP}Harateos" />
    <string id="nyCtbjg6" text="{.MP}Dżamair" />
    <string id="OABjrV1T" text="{.MP}Wioshen" />
    <string id="ODcWVL1a" text="{.MP}Gendirowing{.nnp}" />
    <string id="ODSf45wh" text="{.F}Lead" />
    <string id="ODVepnRR" text="{.MP}Bylorn" />
    <string id="oGf1fUpP" text="{.MP}Terikos{.nnp}" />
    <string id="ogq9oxDn" text="{.MP}Angarys{.nnp}" />
    <string id="OgY3fQKL" text="{.MP}Sasal" />
    <string id="oKeoaDcF" text="{.MP}Garmund" />
    <string id="OL6fbZRY" text="{.MP}Paltos{.nnp}" />
    <string id="OLLYkaWd" text="{.MP}Asralowing{.nnp}" />
    <string id="oPmn1SHy" text="{.MP}Zuwan" />
    <string id="oQCZp9qv" text="{.MP}Eumenys" />
    <string id="OQLPPwrL" text="{.F}Osea" />
    <string id="OqOnfdYv" text="{.MP}Erigaj" />
    <string id="ORJZJYt7" text="{.MP}Czurig" />
    <string id="OrUdifEU" text="{.MP}Jatanowing{.nnp}" />
    <string id="OsjlCBYZ" text="{.F}Saralind" />
    <string id="oT8cTkjz" text="{.MP}Gawan" />
    <string id="oY2rbPH2" text="Banu Jurib" />
    <string id="oyxam3bN" text="{.MP}Blag" />
    <string id="p1dFvTAc" text="dey {ORIGIN_SETTLEMENT}" />
    <string id="P1zsoSPN" text="{.MP}Rowarion" />
    <string id="p4BMhcsQ" text="{.F}Iara" />
    <string id="PbxaX8F5" text="{.MP}Otalotos{.nnp}" />
    <string id="PdK2pGIb" text="{.F}Jesza" />
    <string id="PDK4FHAx" text="{.MP}Suwis" />
    <string id="pDNlFlc0" text="{.MP}Alcza" />
    <string id="pEvpjIa9" text="{.MP}Bunduk" />
    <string id="pfAkvdYc" text="{.MP}Gorgi" />
    <string id="PhdzZKu0" text="{.MP}Ger" />
    <string id="PisfwOUb" text="{.MP}Dżagutaj" />
    <string id="pK5nYd3m" text="fen Ailat" />
    <string id="PknomRIt" text="{.MP}Madwan" />
    <string id="PlGiSfwr" text="{.F}Ilen" />
    <string id="PNR2CvvX" text="{.F}Itikala" />
    <string id="ppmUUMY7" text="{.F}Sigatruda" />
    <string id="ppQbB9BH" text="fen Aertus" />
    <string id="pqlMxWoM" text="{.MP}Alek" />
    <string id="pRA9EzNv" text="{.MP}Akapanos{.nnp}" />
    <string id="PS4mJwUV" text="{.MP}Isilkred" />
    <string id="ptXbItT1" text="{.MP}Nangkut{.nnp}" />
    <string id="PukaQLbR" text="{.F}Dula" />
    <string id="pUQgrcQo" text="{.MP}Brun" />
    <string id="pUvrTrHT" text="{.MP}Gessios{.nnp}" />
    <string id="pVGKlS3W" text="{.F}Istiona" />
    <string id="PvoTcJHa" text="{.MP}Naselos" />
    <string id="pvuNmZF8" text="{.MP}Iwulis" />
    <string id="PwflQ4dc" text="{.MP}Brand" />
    <string id="pXBvPxHI" text="{.F}Penestea" />
    <string id="Py1Jj5mB" text="{.MP}Lorik" />
    <string id="Q26RhEj6" text="{.F}Ifar" />
    <string id="Q2qLCrn2" text="{.MP}Tais" />
    <string id="q8awVLdN" text="{.F}Laita" />
    <string id="Q8gCUmQq" text="{.F}Gyn" />
    <string id="QAHEa5Qr" text="{.F}Petta" />
    <string id="QBtprltg" text="Banu Ajan" />
    <string id="QCiqeUHm" text="{.F}Sabila" />
    <string id="qD72Ya4I" text="{.MP}Zanowing{.nnp}" />
    <string id="qDLWQjuC" text="{.F}Hasawa" />
    <string id="QEw6q3OR" text="{.MP}Jildrim" />
    <string id="qhaBUQQx" text="{.MP}Furenhard" />
    <string id="qhanbPZ9" text="{.MP}Nal" />
    <string id="qJprzW1N" text="{.MP}Airit{.nnp}" />
    <string id="qlqeOSSi" text="fen Leduin" />
    <string id="qMJ7UZvk" text="{.F}Surena" />
    <string id="QNtdUfis" text="{.MP}Wemioros" />
    <string id="QR3aNalC" text="{.MP}Imirza" />
    <string id="qrAEaydU" text="{.MP}Orest" />
    <string id="QtyF13kv" text="{.F}Mata" />
    <string id="qu9adIvZ" text="{.F}Talia" />
    <string id="qUJhzsb1" text="{.F}Jagada" />
    <string id="QumqvLnP" text="{.MP}Ochiwos" />
    <string id="qwab4ICX" text="{.F}Dima" />
    <string id="Qx7ZfdbV" text="{.MP}Kut" />
    <string id="QXaSPsyi" text="fen Uimach" />
    <string id="r0dXXtoU" text="{.MP}Karid" />
    <string id="R11i2uVl" text="{.MP}Kalitos" />
    <string id="R1JECC9r" text="{.F}Zira" />
    <string id="r1RohnC6" text="{.MP}Furkred" />
    <string id="R1yWuIzd" text="{.F}Melia" />
    <string id="r28vZDkN" text="{.F}Wara" />
    <string id="r3GTFdoy" text="{.MP}Oliter" />
    <string id="R6kwhkGk" text="{.MP}Anegis{.nnp}" />
    <string id="R7avnODK" text="{.F}Nasmin" />
    <string id="rahYvT3x" text="{.MP}Ragnar" />
    <string id="rDPExYMQ" text="{.F}Eitar" />
    <string id="RFapQLfR" text="{.MP}Wyszowing{.nnp}" />
    <string id="RfxXnZ8Z" text="{.MP}Kadugan" />
    <string id="rgskh3ve" text="{.MP}Ragid" />
    <string id="RhwPmahK" text="{.MP}Opinates{.nnp}" />
    <string id="rjew3J8a" text="fen Seanel" />
    <string id="Rl3D8X2o" text="{.F}Rategunda" />
    <string id="RMoQ7blK" text="{.MP}Akadan" />
    <string id="rmpKsJwg" text="{.MP}Nuldan" />
    <string id="RohgLdMp" text="{.MP}Asugan" />
    <string id="RpDv3cGI" text="{.MP}Rymanowing{.nnp}" />
    <string id="RrdzC0Mx" text="{.F}Kalata" />
    <string id="rTGmgm4b" text="{.MP}Joren" />
    <string id="rtHgoGvb" text="{.MP}Siwur" />
    <string id="rtljufhM" text="{.F}Mariwyn" />
    <string id="RuxlFoDa" text="{.MP}Unterik" />
    <string id="Rvww4Kxi" text="{.MP}Korstases{.nnp}" />
    <string id="RwMtFwWt" text="{.F}Bilik" />
    <string id="RWTcOnCF" text="{.MP}Worard" />
    <string id="RZ5bYYmX" text="{.F}Lisarad" />
    <string id="sa0YrXiv" text="{.F}Azareh" />
    <string id="sAa3o3vw" text="Banu Taruk" />
    <string id="scCmMFeI" text="{.F}Ekadria" />
    <string id="SDSbjMSj" text="{.MP}Kuruntaj" />
    <string id="Se7U6BSK" text="{.F}Uluen" />
    <string id="sEgUB3jW" text="{.F}Deasora" />
    <string id="sF0H1hEV" text="{.MP}Halgard" />
    <string id="SFDdq8GH" text="{.F}Holudżin" />
    <string id="SGFsmCJa" text="Banu Tammar" />
    <string id="sgIlIqrI" text="{.MP}Goronos{.nnp}" />
    <string id="sGYHxIub" text="{.MP}Reamald" />
    <string id="SHXt3kC5" text="{.F}Roszane" />
    <string id="sIBcdaxD" text="{.F}Soren" />
    <string id="SIJpKiGq" text="{.F}Aila" />
    <string id="sIjuSRYT" text="{.MP}Fredakard" />
    <string id="SJJobqeR" text="Banu Widas" />
    <string id="skIyo33b" text="fen Kalrain" />
    <string id="sn3JPGJA" text="{.MP}Natu" />
    <string id="SNjqoBfZ" text="{.F}Nawa" />
    <string id="SOkQ7b7r" text="{.MP}Taqir" />
    <string id="SQji7Ek8" text="fen Fiaszan" />
    <string id="StJ9aR91" text="{.MP}Kadfin" />
    <string id="SVruYnYb" text="{.F}Selag" />
    <string id="SvyDUmw3" text="{.MP}Wianimir" />
    <string id="sWBxHVzp" text="{.MP}Merović" />
    <string id="SWM5cmVP" text="{.MP}Ento" />
    <string id="sWRKG0e1" text="{.MP}Iltas" />
    <string id="swzCKty3" text="{.MP}Karsten" />
    <string id="t0TXa7Fp" text="{.MP}Wuldrat" />
    <string id="T1mpRVib" text="fen Morain" />
    <string id="T1xNyk3H" text="fen Brachar" />
    <string id="t36SVqzP" text="{.MP}Bustamys{.nnp}" />
    <string id="t4OvAlBq" text="{.F}Nus" />
    <string id="t63KuB1X" text="{.MP}Sutain" />
    <string id="t6e4wphB" text="{.F}Weta" />
    <string id="T9bXZA0W" text="{.MP}Cynak" />
    <string id="Ta0zl7o1" text="{.MP}Gutlans" />
    <string id="tCy0qwXp" text="{.F}Hikara" />
    <string id="tDaWbJlY" text="{.MP}Oranarit{.nnp}" />
    <string id="tGaIU6Jk" text="{.MP}Gunteryk" />
    <string id="tGEChxdb" text="{.MP}Aczanowing{.nnp}" />
    <string id="tGhrpQ0D" text="{.F}Hyradia" />
    <string id="tgVJZ1Uc" text="{.MP}Hekaron" />
    <string id="TIhFAZld" text="Banu Idżaraz" />
    <string id="TjvbLQRT" text="{.MP}Daszan" />
    <string id="tKUIAmbV" text="{.MP}Fjomanowing{.nnp}" />
    <string id="TLZKQSb1" text="{.MP}Egan" />
    <string id="TN5MjMJU" text="{.F}Risa" />
    <string id="TNI6qRbQ" text="{.MP}Astretydes{.nnp}" />
    <string id="tOmtchNx" text="{.MP}Tanir" />
    <string id="tp3yvlYW" text="{.MP}Temir" />
    <string id="tPG5uf4C" text="{.MP}Boszit{.nnp}" />
    <string id="tTmqewol" text="{.F}Ifrain" />
    <string id="TUQlQWzb" text="{.MP}Origand" />
    <string id="tW6wEhuR" text="{.MP}Hirobert" />
    <string id="TWykLiFB" text="{.F}Gwet" />
    <string id="txEVb6TR" text="fen Gwaitor" />
    <string id="TxKnmzwT" text="{.MP}Urien" />
    <string id="u154THZL" text="{.MP}Dżalsjut{.nnp}" />
    <string id="u3ZpGN5e" text="{.MP}Jucha" />
    <string id="U9kQ2sTU" text="{.MP}Tasyks{.nnp}" />
    <string id="UAHJ2jTp" text="{.F}Mahail" />
    <string id="UaOynysV" text="{.F}Agna" />
    <string id="uAS832LM" text="{.MP}Ydwin" />
    <string id="Ub0awU1n" text="{.F}Ewin" />
    <string id="UcteBSP6" text="{.F}Asi" />
    <string id="Ud1AMybr" text="Sturgijczycy pochodzą z północnych lasów leżących nad mroźnym Morzem Bjalskim. Przez stulecia w izolacji zamieszkiwali mroczne lasy, ich liczebność zaś ograniczały niosące śmierć zimy. Jednak w miarę jak Cesarstwo obejmowało coraz większą część kontynentu kalradyjskiego, w knieje zaczęli zapuszczać się kupcy poszukujący miodu, rudy darniowej i – przede wszystkim – futer. Na brzegach licznych zatok i jezior wyrosły wielkie miasta łączące sturgijskie ziemie ze światem zewnętrznym oraz przyciągające awanturników z wybrzeża, stepów i północnych krain. Książęta i bojarowie tych ziem zwracają teraz oczy poza granice swoich włości, a o ich wojennym podejściu do biznesu i biznesowym podejściu do wojny krążą już legendy." />
    <string id="UgA0uoFA" text="{.MP}Tabur" />
    <string id="UJTCzvOt" text="{.F}Elin" />
    <string id="UKcaINTn" text="Banu Chaszal" />
    <string id="ulBMajMY" text="{.F}Czeczek" />
    <string id="UlPJ9OYH" text="{.MP}Nidr" />
    <string id="UlQWfDsU" text="fen Teikolar" />
    <string id="ulua6Frr" text="{.MP}Ortol" />
    <string id="USkaRPEQ" text="{.MP}Samandry" />
    <string id="UtfVuNN0" text="{.F}Wiwein" />
    <string id="uwalgjVy" text="Banu Dilis" />
    <string id="uYbmhjI6" text="{.F}Ramira" />
    <string id="UYqwbjTP" text="{.MP}Iskanowing{.nnp}" />
    <string id="V3QHxJb1" text="{.MP}Polmark" />
    <string id="v5bWtXj1" text="Plemiona żyjące na wielkim morzu traw na wschód od Cesarstwa noszą wiele nazw: Naczaganowie, Arkici, Kergici, Karakergici. Ludzie z zewnątrz określają ich jednak zwykle po prostu jako Huzajczyków, a więc nazwą klanu, który w ciągu ostatnich dwóch pokoleń zmienił grupy koczowników w potężną armię. Kiedy Urkun Wielki przyjął kapitulację leżących na obrzeżach stepu miast handlowych, nakazał swoim nojonom zrezygnować z nomadycznego trybu życia. Otrzymali włości i środki na budowę fortec, zostali też zachęceni, by czynić miejscowych rolników swoimi poddanymi. Plemiona konfederacji huzajskiej wciąż jednak zachowują wiele ze swych koczowniczych tradycji, a w ich osadach, będących na poły wioskami, na poły obozowiskami, obok wież z glinianych cegieł wciąż stoją jurty." />
    <string id="v7tfA4y6" text="{.F}Sijafan" />
    <string id="v9B50R0Q" text="{.MP}Akarion" />
    <string id="Va35TmQW" text="{.MP}Igrunowing{.nnp}" />
    <string id="VaqB0x4K" text="{.F}Dranga" />
    <string id="vb2rv3OK" text="{.F}Una" />
    <string id="vDGYMAmm" text="{.MP}Dermot" />
    <string id="vdOWVAoz" text="{.MP}Altezjos{.nnp}" />
    <string id="VJbAdJe4" text="{.MP}Purios" />
    <string id="vjeyAchh" text="{.F}Deragunda" />
    <string id="vN0cSBD3" text="{.MP}Szakor" />
    <string id="VN1D1Qps" text="{.MP}Welanor" />
    <string id="VP9hqkxO" text="{.MP}Aedid" />
    <string id="Vp9n86Wy" text="{.MP}Lezanowing{.nnp}" />
    <string id="vPlwv7Vj" text="{.MP}Miloch" />
    <string id="vQMRjzmO" text="{.MP}Pias" />
    <string id="VQYTvnfW" text="{.MP}Durold" />
    <string id="VV6p47Ee" text="Banu Arumak" />
    <string id="VVpv4El5" text="fen Sachta" />
    <string id="VVT3bMc2" text="{.MP}Regbold" />
    <string id="VWSA8EVV" text="{.F}Gwennein" />
    <string id="vYQ2SMEv" text="{.F}Siban" />
    <string id="VYWtQe8r" text="{.MP}Warmond" />
    <string id="vz038vX7" text="{.F}Achita" />
    <string id="w1a9E7a9" text="{.F}Fiasyn" />
    <string id="W1yur1cf" text="{.F}Kaczin" />
    <string id="W1ZpjgQO" text="{.MP}Rauko" />
    <string id="w4u0LxQb" text="{.MP}Lowanides{.nnp}" />
    <string id="W4VYqLYc" text="{.F}Weragid" />
    <string id="W6htECeI" text="{.MP}Tawin" />
    <string id="W6UjOymF" text="{.F}Lucibalda" />
    <string id="w9fY8ab4" text="{.F}Arigun" />
    <string id="wCYpyCab" text="{.F}Sotylda" />
    <string id="wDRBoiTC" text="{.F}Iliset" />
    <string id="wERVdmjj" text="{.F}Sulnaz" />
    <string id="wf4cGf3B" text="{.MP}Bowidor" />
    <string id="WFfbxYu5" text="Banu Zus" />
    <string id="wlwVPqjP" text="{.MP}Uln" />
    <string id="WNb0Bw0e" text="{.MP}Kawyl" />
    <string id="WNu6dKHe" text="{.F}Lliari" />
    <string id="WP63fA7r" text="{.F}Alkiria" />
    <string id="WpTXwQw1" text="{.MP}Wuoni" />
    <string id="wQJGxBJI" text="{.MP}Hoftalamos" />
    <string id="wRVVs7t4" text="Banu Sirsan" />
    <string id="wsCMwqFw" text="{.MP}Peribard" />
    <string id="WtIBqZr6" text="{.MP}Wanter" />
    <string id="wuGPSje6" text="{.MP}Grewet" />
    <string id="Wuiog2eu" text="{.F}Brigis" />
    <string id="WuMGWUJ7" text="{.F}Addien" />
    <string id="wvLyCxZz" text="{.MP}Ulward" />
    <string id="wYPWlhme" text="{.F}Zandina" />
    <string id="X0kKBzsW" text="Choć Kalradią nazywa się cały zdominowany przez Cesarstwo kontynent, miano Kalradyjczyka dotyczy tylko mieszkańców tego państwa. Tysiąc lat temu byli oni niepozornym plemieniem żyjącym wśród wzgórz między południowym morzem a batańskimi lasami. Od sąsiadów odróżniała ich jedna tradycja: Kalradoi, jak się wówczas nazywali, nie mieli królów. Od zawsze porywała ich idea samorządności, równowagi między ochroną wolności jednostki a potrzebami kraju. Być może to właśnie zapewniło im drobną przewagę w niemających końca wojnach między poszczególnymi miastami. Armie wytrzymywały w polu odrobinę dłużej i odrobinę szybciej wracały do siebie po porażce. Niektórzy sąsiedzi połączyli z nimi siły, inni zaś zostali pokonani. Ostatecznie Kalradyjczycy stworzyli imperium, które wyewoluowało w ustrój stanowiący pod każdym względem – oprócz nazwy – monarchię. Ich przywódcy nie są już dostojnymi starszymi, lecz wielkimi posiadaczami ziemskimi z włościami na całym kontynencie. Siłą ich armii nie jest dzisiaj złożona z obywateli piechota, lecz ciężko opancerzeni katafrakci opłacani przez bogaczy. Nadal jednak bardzo poważnie traktują swoje tradycje obywatelskie i wierzą, że kalradyjskie ideały byłyby w stanie zjednoczyć kontynent w pokoju, gdyby tylko „barbarzyńcy” z państw ościennych zgodzili się im podporządkować." />
    <string id="x1mVOiYC" text="{.MP}Leotold" />
    <string id="X4ZS4q8L" text="{.F}Jasana" />
    <string id="XAF12HV0" text="{.F}Wikka" />
    <string id="xft6bgja" text="{.F}Asza" />
    <string id="xg8habbc" text="{.MP}Alagur" />
    <string id="XJZJIZ9Q" text="{.MP}Czolokowing{.nnp}" />
    <string id="Xo1ZwCmu" text="{.MP}Mor" />
    <string id="Xp0RHe1F" text="{.MP}Wadikand" />
    <string id="xp1wiXvW" text="{.MP}Genalf" />
    <string id="xqC8yfah" text="{.F}Cidre" />
    <string id="XQfYxgti" text="{.MP}Nimanowing{.nnp}" />
    <string id="xu0MkWUY" text="{.MP}Olgurnond" />
    <string id="xUSeJEd6" text="{.MP}Wahan" />
    <string id="XWqBgFzc" text="{.MP}Forydes{.nnp}" />
    <string id="XxSD6GAu" text="{.MP}Jun" />
    <string id="xyIDKleR" text="{.MP}Said" />
    <string id="xyKumbJI" text="{.MP}Kalastydes{.nnp}" />
    <string id="Y49TwXg4" text="{.F}Sionna" />
    <string id="y7rQ4USD" text="{.MP}Perin" />
    <string id="Y9030sOS" text="{.F}Dartia" />
    <string id="Y9qYt71a" text="{.MP}Balikowing{.nnp}" />
    <string id="YahyjyK5" text="{.F}Gudra" />
    <string id="ybDa8V4I" text="{.F}Adalis" />
    <string id="yCfxqfdA" text="{.MP}Bachar" />
    <string id="yckGOfLB" text="{.F}Islena" />
    <string id="yd39Cman" text="{.F}Ruwa" />
    <string id="YdMwMdyf" text="{.MP}Dumat" />
    <string id="YEqDIbir" text="{.F}Oana" />
    <string id="YeQlI2Yj" text="{.MP}Mizam" />
    <string id="yhCgI9ph" text="{.F}Magna" />
    <string id="yhfJVEe0" text="{.MP}Felenos" />
    <string id="yhLbBk1D" text="{.MP}Sorocz" />
    <string id="YIpKt79X" text="{.MP}Kusr" />
    <string id="YiVqz8eW" text="{.MP}Kalryk" />
    <string id="YJ6JKs9O" text="{.MP}Kiorynowing{.nnp}" />
    <string id="yJz9AxjY" text="{.F}Rinana" />
    <string id="Yl3c9WaM" text="{.MP}Salastrys" />
    <string id="Yl4EsjBg" text="{.F}Drusabalda" />
    <string id="YlVmRzCI" text="{.F}Atafled" />
    <string id="ynsUwp1h" text="{.MP}Denek" />
    <string id="yrYO33f8" text="Banu Qaram" />
    <string id="YRzakgRB" text="{.MP}Bidal" />
    <string id="ystHsOQi" text="{.MP}Wilmarand" />
    <string id="YSwz9JUr" text="{.MP}Eltert" />
    <string id="yToKqfa3" text="{.MP}Szumsan" />
    <string id="yUuM8a0j" text="{.MP}Boranowing{.nnp}" />
    <string id="YVVCaQE5" text="{.F}Tera" />
    <string id="ywlfoIUX" text="{.MP}Merteon" />
    <string id="YwQbvO9O" text="{.F}Lulia" />
    <string id="YwwaCRSr" text="{.F}Barisza" />
    <string id="Z261F0mj" text="{.MP}Hamezan" />
    <string id="z2KE7glc" text="{.F}Tylea" />
    <string id="z2Oqk8aq" text="{.MP}Maregowing{.nnp}" />
    <string id="z3rmbOSO" text="{.MP}Gawin" />
    <string id="z5llJ2C0" text="{.MP}Norogur" />
    <string id="Z5NIRUPc" text="{.F}Idruna" />
    <string id="z6GIOwi9" text="{.MP}Malbert" />
    <string id="Z7GxyIaC" text="{.MP}Borun" />
    <string id="zAC87rrQ" text="{.F}Tora" />
    <string id="zCaeJ7GC" text="{.MP}Tul" />
    <string id="zcXPVYs5" text="{.F}Deteuda" />
    <string id="zDhuJw7r" text="{.F}Taralun" />
    <string id="ZEwqRhHO" text="Banu Hund" />
    <string id="ZgGnqkki" text="{.F}Beniset" />
    <string id="ZJjgZVHq" text="{.MP}Endry" />
    <string id="zLl1UEYM" text="{.MP}Zem" />
    <string id="Zm0Ee6sp" text="{.MP}Azadun" />
    <string id="ZM8fmXGb" text="{.MP}Badulf" />
    <string id="ZNUooJ48" text="{.MP}Tebegun{.nnp}" />
    <string id="ZP7ONkec" text="{.MP}Egen" />
    <string id="ZPHdPglH" text="{.F}Raksana" />
    <string id="zSL3MgNQ" text="{.F}Ilzar" />
    <string id="ZSraCpCs" text="{.MP}Lakem" />
    <string id="zTEnQULc" text="{.MP}Tagaj" />
    <string id="ZwOT9J49" text="{.MP}Judżit{.nnp}" />
    <string id="zYAl76GW" text="{.MP}Borytor" />
    <string id="zyoEpXek" text="{.MP}Humalgart" />
  </strings>
</base>